sthenos/__init__.py
sthenos/cli.py
sthenos/bin/sthenos-linux
sthenos/bin/sthenos-mac
sthenos/bin/sthenos.exe
sthenos-0.1.31.dist-info/licenses/LICENSE
sthenos-0.1.31.dist-info/METADATA
sthenos-0.1.31.dist-info/WHEEL
sthenos-0.1.31.dist-info/entry_points.txt
sthenos-0.1.31.dist-info/top_level.txt
sthenos-0.1.31.dist-info/RECORD
