Metadata-Version: 2.4
Name: sthenos
Version: 0.1.31
Summary: A Python-scriptable load testing tool (Go binary wrapper)
Author-email: Aldo Richard Santillán Echevarría <richard.24.se@gmail.com>
License: STHENOS LICENSE
Project-URL: Homepage, https://github.com/richard24se/Sthenos
Project-URL: Bug Tracker, https://github.com/richard24se/Sthenos/issues
Keywords: load-testing,k6,performance,benchmark,go,python,scriptable
Classifier: Programming Language :: Python :: 3
Classifier: Programming Language :: Go
Classifier: Operating System :: OS Independent
Classifier: License :: Other/Proprietary License
Classifier: Topic :: Software Development :: Testing :: Traffic Generation
Requires-Python: >=3.7
License-File: LICENSE
Dynamic: license-file
